{
  "project_info": {
    "project_number": "555372235169",
    "project_id": "barter-app-4ac31",
    "storage_bucket": "barter-app-4ac31.appspot.com"
  },
  "client": [
    {
      "client_info": {
        "mobilesdk_app_id": "1:555372235169:android:cdee02f402dd31662da3e0",
        "android_client_info": {
          "package_name": "com.example.myapplication"
        }
      },
      "oauth_client": [],
      "api_key": [
        {
          "current_key": "AIzaSyBE2Tst6vVOqtcVMABhhVwrAeG8BdKQDKw"
        }
      ],
      "services": {
        "appinvite_service": {
          "other_platform_oauth_client": []
        }
      }
    }
  ],
  "configuration_version": "1"
}